{".class": "MypyFile", "_fullname": "fms.apps", "is_partial_stub_package": false, "is_stub": false, "names": {".class": "SymbolTable", "AppConfig": {".class": "SymbolTableNode", "kind": "Gdef", "node": {".class": "Var", "flags": ["is_suppressed_import"], "fullname": "fms.apps.AppConfig", "name": "AppConfig", "type": {".class": "AnyType", "missing_import_name": "fms.apps.AppConfig", "source_any": null, "type_of_any": "from_unimported_type"}}}, "FmsConfig": {".class": "SymbolTableNode", "kind": "Gdef", "node": {".class": "TypeInfo", "_promote": null, "abstract_attributes": [], "bases": ["builtins.object"], "declared_metaclass": null, "defn": {".class": "ClassDef", "fullname": "fms.apps.FmsConfig", "name": "FmsConfig", "type_vars": []}, "flags": ["fallback_to_any"], "fullname": "fms.apps.FmsConfig", "metaclass_type": null, "metadata": {}, "module_name": "fms.apps", "mro": ["fms.apps.FmsConfig", "builtins.object"], "names": {".class": "SymbolTable", "name": {".class": "SymbolTableNode", "kind": "Mdef", "node": {".class": "Var", "flags": ["is_initialized_in_class"], "fullname": "fms.apps.FmsConfig.name", "name": "name", "type": "builtins.str"}}}, "tuple_type": null, "type_vars": [], "typeddict_type": null}}, "__doc__": {".class": "SymbolTableNode", "kind": "Gdef", "node": {".class": "Var", "flags": [], "fullname": "fms.apps.__doc__", "name": "__doc__", "type": "builtins.str"}}, "__file__": {".class": "SymbolTableNode", "kind": "Gdef", "node": {".class": "Var", "flags": [], "fullname": "fms.apps.__file__", "name": "__file__", "type": "builtins.str"}}, "__name__": {".class": "SymbolTableNode", "kind": "Gdef", "node": {".class": "Var", "flags": [], "fullname": "fms.apps.__name__", "name": "__name__", "type": "builtins.str"}}, "__package__": {".class": "SymbolTableNode", "kind": "Gdef", "node": {".class": "Var", "flags": [], "fullname": "fms.apps.__package__", "name": "__package__", "type": "builtins.str"}}}, "path": "/home/webmalc/Projects/maxibooking-billing/fms/apps.py"}
